{
  "project_info": {
    "project_number": "101603676767",
    "project_id": "chatapp-c71b6",
    "storage_bucket": "chatapp-c71b6.appspot.com"
  },
  "client": [
    {
      "client_info": {
        "mobilesdk_app_id": "1:101603676767:android:ff623eb89f2243be2441ea",
        "android_client_info": {
          "package_name": "com.bignerdranch.android.chatapp"
        }
      },
      "oauth_client": [
        {
          "client_id": "101603676767-k2h1m2216os1d24kirelat693g5fpvd3.apps.googleusercontent.com",
          "client_type": 3
        }
      ],
      "api_key": [
        {
          "current_key": "AIzaSyCgeYVayyBGi5ZYKCDceF9gNIDuuNrYAF8"
        }
      ],
      "services": {
        "appinvite_service": {
          "other_platform_oauth_client": [
            {
              "client_id": "101603676767-k2h1m2216os1d24kirelat693g5fpvd3.apps.googleusercontent.com",
              "client_type": 3
            }
          ]
        }
      }
    }
  ],
  "configuration_version": "1"
}